{
  "project_info": {
    "project_number": "679413461072",
    "firebase_url": "https://cse438-project4-bf2c9.firebaseio.com",
    "project_id": "cse438-project4-bf2c9",
    "storage_bucket": "cse438-project4-bf2c9.appspot.com"
  },
  "client": [
    {
      "client_info": {
        "mobilesdk_app_id": "1:679413461072:android:886ffbaed7b666d5",
        "android_client_info": {
          "package_name": "com.example.cse438_project4"
        }
      },
      "oauth_client": [
        {
          "client_id": "679413461072-fv6a2r57uulo3klv901aog7lgdvfaacs.apps.googleusercontent.com",
          "client_type": 1,
          "android_info": {
            "package_name": "com.example.cse438_project4",
            "certificate_hash": "d07d3146e0b7f8e4c991b3536c4e01330947df73"
          }
        },
        {
          "client_id": "679413461072-7o1eo9dp48rrdcs8vafauopjonls5vr7.apps.googleusercontent.com",
          "client_type": 3
        }
      ],
      "api_key": [
        {
          "current_key": "AIzaSyDSXvtQqs1xTHdpol64hHM0f2dNLV3ii2Q"
        }
      ],
      "services": {
        "analytics_service": {
          "status": 1
        },
        "appinvite_service": {
          "status": 2,
          "other_platform_oauth_client": [
            {
              "client_id": "679413461072-7o1eo9dp48rrdcs8vafauopjonls5vr7.apps.googleusercontent.com",
              "client_type": 3
            }
          ]
        },
        "ads_service": {
          "status": 2
        }
      }
    }
  ],
  "configuration_version": "1"
}